hypergo/__init__.py
hypergo/azure_service_bus_connection.py
hypergo/azure_service_bus_executor.py
hypergo/config.py
hypergo/connection.py
hypergo/context.py
hypergo/custom_types.py
hypergo/executor.py
hypergo/graph.py
hypergo/hypergo_cli.py
hypergo/hypergo_click.py
hypergo/hypergo_cmd.py
hypergo/local_storage.py
hypergo/logger.py
hypergo/mapping.py
hypergo/message.py
hypergo/monitor.py
hypergo/secrets.py
hypergo/service_bus_connection.py
hypergo/stdio_connection.py
hypergo/storage.py
hypergo/transaction.py
hypergo/transform.py
hypergo/utility.py
hypergo/version.py
hypergo/connectors/__init__.py
hypergo/connectors/azure_application_insights.py
hypergo/loggers/__init__.py
hypergo/loggers/azure_logger.py
hypergo/loggers/base_logger.py
hypergo/loggers/hypergo_logger.py
hypergo/metrics/__init__.py
hypergo/metrics/base_metrics.py
hypergo/metrics/custom_metrics.py
hypergo/metrics/hypergo_metrics.py
hypergo/standard_components/__init__.py
hypergo/standard_components/pipeline_orchestrator/__init__.py
hypergo/standard_components/pipeline_orchestrator/__main__.py
hypergo/standard_components/transaction_manager/__init__.py
hypergo/standard_components/transaction_manager/__main__.py
hypergo-0.3.19.dist-info/LICENSE
hypergo-0.3.19.dist-info/METADATA
hypergo-0.3.19.dist-info/WHEEL
hypergo-0.3.19.dist-info/entry_points.txt
hypergo-0.3.19.dist-info/top_level.txt
hypergo-0.3.19.dist-info/RECORD
